rcute_scratch_link/__init__.py
rcute_scratch_link/__main__.py
rcute_scratch_link/server.py
rcute_scratch_link/version.py
rcute_scratch_link-0.0.1.dist-info/DESCRIPTION.rst
rcute_scratch_link-0.0.1.dist-info/METADATA
rcute_scratch_link-0.0.1.dist-info/RECORD
rcute_scratch_link-0.0.1.dist-info/WHEEL
rcute_scratch_link-0.0.1.dist-info/metadata.json
rcute_scratch_link-0.0.1.dist-info/top_level.txt
