Metadata-Version: 2.0
Name: rcute-scratch-link
Version: 0.0.1
Summary: scratch link for rcute robots
Home-page: https://github.com/r-cute/rcute-scratch-link
Author: Huang Yan
Author-email: hyansuper@foxmail.com
License: MIT
Platform: UNKNOWN
Classifier: Programming Language :: Python :: 3.7
Classifier: License :: OSI Approved :: MIT License
Classifier: Operating System :: OS Independent
Requires-Dist: opencv-python
Requires-Dist: rcute-ai
Requires-Dist: rcute-cozmars
Requires-Dist: websockets
Requires-Dist: wsmprpc (>=1.1.3)
Requires-Dist: zeroconf
